vboxinit/__init__.py
vboxinit/__main__.py
vboxinit/client_config/client_config.py
vboxinit/completers/customCompleter.py
vboxinit/decorators/singleton.py
vboxinit/modules/_utils/_utils.py
vboxinit/modules/_utils/arch.py
vboxinit/modules/_utils/cleanup_network_config.py
vboxinit/modules/_utils/setup_apt_sources.py
vboxinit/modules/docker/docker.py
vboxinit/modules/docker/roles/role.py
vboxinit/modules/docker/templates/daemon/daemon_multi_mirrors.json
vboxinit/modules/docker/templates/gpgkey/debian_gpgkey
vboxinit/modules/docker/templates/gpgkey/ubuntu_gpgkey
vboxinit/modules/kiro/kiro.py
vboxinit/modules/linux_init/base_box_init.py
vboxinit/modules/linux_init/roles/role.py
vboxinit-0.2.10.dist-info/WHEEL
vboxinit-0.2.10.dist-info/entry_points.txt
vboxinit-0.2.10.dist-info/METADATA
vboxinit-0.2.10.dist-info/RECORD
